{
  "cik": "0001820953",
  "ticker": "AFRM",
  "name": "Affirm Holdings, Inc.",
  "detection_reasons": [
    "offshore:bm"
  ],
  "sic": "6141",
  "sicDescription": "Personal Credit Institutions",
  "category": "Large accelerated filer",
  "entityType": "operating",
  "stateOfIncorporation": "NV",
  "ein": "842224323",
  "phone": "(415) 960-1518",
  "website": "",
  "addresses": {
    "mailing": {
      "street1": "650 CALIFORNIA STREET",
      "street2": null,
      "city": "SAN FRANCISCO",
      "stateOrCountry": "CA",
      "zipCode": "94108",
      "stateOrCountryDescription": "CA",
      "isForeignLocation": 0,
      "foreignStateTerritory": null,
      "country": null,
      "countryCode": null
    },
    "business": {
      "street1": "650 CALIFORNIA STREET",
      "street2": null,
      "city": "SAN FRANCISCO",
      "stateOrCountry": "CA",
      "zipCode": "94108",
      "stateOrCountryDescription": "CA",
      "isForeignLocation": null,
      "foreignStateTerritory": null,
      "country": null,
      "countryCode": null
    }
  },
  "latest_filing": {
    "form": "8-K",
    "date": "2025-09-22"
  },
  "filings_count": 610
}
